LICENSE.txt
README.md
setup.py
flyeye/__init__.py
flyeye.egg-info/PKG-INFO
flyeye.egg-info/SOURCES.txt
flyeye.egg-info/dependency_links.txt
flyeye.egg-info/requires.txt
flyeye.egg-info/top_level.txt
flyeye/analysis/__init__.py
flyeye/analysis/correlation.py
flyeye/analysis/spectrogram.py
flyeye/data/__init__.py
flyeye/data/cells.py
flyeye/data/discs.py
flyeye/data/experiments.py
flyeye/data/image.py
flyeye/data/silhouette.py
flyeye/dynamics/__init__.py
flyeye/dynamics/averages.py
flyeye/dynamics/resampling.py
flyeye/dynamics/visualization.py
flyeye/processing/__init__.py
flyeye/processing/alignment.py
flyeye/processing/triangulation.py
flyeye/utilities/__init__.py
flyeye/utilities/iteration.py
flyeye/utilities/string_handling.py