Metadata-Version: 2.1
Name: flyeye
Version: 0.6
Summary: Analysis package for FlyEye Silhouette data.
Home-page: https://sbernasek.github.io/flyeye/
Author: Sebastian Bernasek
Author-email: sebastian@u.northwestern.com
License: MIT
Platform: UNKNOWN
Requires-Python: >=3
Provides-Extra: frequency_detection
